PermutationImportance/__init__.py
PermutationImportance/abstract_runner.py
PermutationImportance/data_verification.py
PermutationImportance/error_handling.py
PermutationImportance/metrics.py
PermutationImportance/multiprocessing_utils.py
PermutationImportance/permutation_importance.py
PermutationImportance/result.py
PermutationImportance/scoring_strategies.py
PermutationImportance/selection_strategies.py
PermutationImportance/sequential_selection.py
PermutationImportance/sklearn_api.py
PermutationImportance/utils.py
permutation_importance/__init__.py
permutation_importance/importance_result.py
permutation_importance/scorers.py
permutation_importance/utilities.py
permutation_importance/variable_importance.py
src/__init__.py
src/abstract_runner.py
src/data_verification.py
src/error_handling.py
src/metrics.py
src/permutation_importance.py
src/result.py
src/scoring_strategies.py
src/selection_strategies.py
src/sequential_selection.py
src/sklearn_api.py
src/utils.py
PermutationImportance-1.2.1.8.dist-info/METADATA
PermutationImportance-1.2.1.8.dist-info/WHEEL
PermutationImportance-1.2.1.8.dist-info/top_level.txt
PermutationImportance-1.2.1.8.dist-info/RECORD
