Metadata-Version: 2.1
Name: PermutationImportance
Version: 1.2.1.8
Summary: Important variables determined through data-based variable importance methods
Home-page: https://github.com/gelijergensen/PermutationImportance
Author: G. Eli Jergensen
Author-email: gelijergensen@ou.edu
License: MIT
Keywords: predictor importance,variable importance,model evaluation
Platform: UNKNOWN
Classifier: Development Status :: 4 - Beta
Classifier: Intended Audience :: Science/Research
Classifier: License :: OSI Approved :: MIT License
Classifier: Programming Language :: Python :: 2.7
Classifier: Programming Language :: Python :: 3
Classifier: Operating System :: OS Independent
Classifier: Topic :: Scientific/Engineering :: Information Analysis
Requires-Python: >=2.7, !=3.0.*, !=3.1.*, !=3.2.*, !=3.3.*, !=3.4.*, !=3.5.*
Requires-Dist: numpy
Requires-Dist: pandas
Requires-Dist: scipy (==1.1.0)
Requires-Dist: scikit-learn
